y2hscore/__init__.py
y2hscore/__main__.py
y2hscore/gui/canvas.py
y2hscore/gui/panel.py
y2hscore/gui/window.py
y2hscore/io/file.py
y2hscore/io/folder.py
y2hscore/model/cnn.py
y2hscore/model/weights/conv_1_bias.npy
y2hscore/model/weights/conv_1_kernel.npy
y2hscore/model/weights/conv_2_bias.npy
y2hscore/model/weights/conv_2_kernel.npy
y2hscore/model/weights/conv_3_bias.npy
y2hscore/model/weights/conv_3_kernel.npy
y2hscore/model/weights/conv_4_bias.npy
y2hscore/model/weights/conv_4_kernel.npy
y2hscore/model/weights/conv_5_bias.npy
y2hscore/model/weights/conv_5_kernel.npy
y2hscore/model/weights/conv_6_bias.npy
y2hscore/model/weights/conv_6_kernel.npy
y2hscore/model/weights/conv_7_bias.npy
y2hscore/model/weights/conv_7_kernel.npy
y2hscore/model/weights/conv_8_kernel.npy
y2hscore/processing/draw.py
y2hscore/processing/grid.py
y2hscore-0.1.0.dist-info/METADATA
y2hscore-0.1.0.dist-info/WHEEL
y2hscore-0.1.0.dist-info/top_level.txt
y2hscore-0.1.0.dist-info/RECORD
