Metadata-Version: 2.4
Name: y2hscore
Version: 0.1.0
Summary: Y2HScore runs with python -m y2hscore
Author-email: "INET, Helmholtz Munich" <inet@helmholtz-munich.com>
Requires-Python: >=3.10
Requires-Dist: opencv-python<5.0,>=4.10
Requires-Dist: numpy>=2.2
